[1,["ecpdLyjvZBwrvm+cedCcQy","57Z892e3NCSIUjIxO6/qao","e5COw6GjpCLIVqc3iajDle","b2GD9KZIlAwYQdbEQnZZBs","e5DwgpEFlAPrbwqIOUEgdT","e4Ha1mgXVDIaz4pEMwEMv8","f1bR6B62BAF5k3JddsdNZq","4c3LlxyPdFzKmDpsE6jKcW","edIWQucYFJH74QloCDiVHC","e70chFMS9Abq656dHMK0Tk","c44LrhThRHxrfQipW3rj/b","17oboXcghP1a6HFE23z6Zo","f8CSd7A2RBVpYxK7VeybbD","60jhhMxv1FB5+NOswLa7i3","80GFl9NeFCGYBmaKktG0sh"],["node","_spriteFrame","_textureSetter","loadingProgress","scene","_parent"],["cc.SpriteFrame",["cc.Node",["_name","_id","_components","_contentSize","_trs","_parent","_children"],1,9,5,7,1,2],["cc.Sprite",["_sizeMode","_type","_fillRange","node","_materials","_spriteFrame"],0,1,3,6],["cc.SceneAsset",["_name","asyncLoadAssets"],1],["cc.Node",["_name","_parent","_components","_contentSize","_anchorPoint","_trs"],2,1,2,5,5,7],["cc.Canvas",["node","_designResolution"],3,1,5],["cc.Widget",["_alignFlags","node"],2,1],["f7216kgOABAc5tb4fIcYRtq",["node","loadingProgress"],3,1,1],["cc.Scene",["_name","_active","_children","_anchorPoint","_trs"],1,2,5,7],["cc.Camera",["_clearFlags","_depth","node"],1,1],["cc.Button",["node","clickEvents"],3,1,9],["cc.ClickEvent",["_componentId","handler","target"],1,1]],[[2,3,4,5,1],[1,0,5,2,3,4,2],[1,0,5,6,2,3,4,2],[3,0,1,3],[1,0,1,6,2,3,4,3],[1,0,5,2,4,2],[1,0,5,2,3,2],[4,0,1,2,3,4,5,2],[5,0,1,1],[6,0,1,2],[2,0,3,4,5,2],[2,1,0,2,3,4,4],[7,0,1,1],[8,0,1,2,3,4,3],[9,0,1,2,3],[10,0,1,1],[11,0,1,2,3]],[[[[3,"Loading",null],[4,"Canvas","389ZbEtthECZ0vw+UFQUe5",[-3,-4,-5,-6,-7,-8,-9],[[8,-1,[5,1136,640]],[9,45,-2]],[5,1136,640],[568,320,0,0,0,0,1,1,1,1]],[2,"bgNode",1,[-13],[[10,2,-10,[3],4],[12,-12,-11]],[5,462,46],[0,-207,0,0,0,0,1,1,1,1]],[2,"clear",1,[-15],[[0,-14,[5],6]],[5,541,115],[0,-113,0,0,0,0,1,1,1,1]],[13,"New Node",false,[1],[0,0,0],[0,0,0,0,0,0,1,1,1,1]],[5,"Main Camera",1,[[14,7,-1,-16]],[0,0,363.73066958946424,0,0,0,1,1,1,1]],[6,"loadBg",1,[[0,-17,[0],1]],[5,1386,640]],[1,"btn",3,[[15,-18,[[16,"f7216kgOABAc5tb4fIcYRtq","clickRestart",2]]]],[5,90,24],[38,21,0,0,0,0,1,1,1,1]],[7,"pro",2,[-19],[5,450,34],[0,0,0.5],[-225,0,0,0,0,0,1,1,1,1]],[11,3,2,1,8,[2]],[1,"7",1,[[0,-20,[7],8]],[5,828,18],[0,-260,0,0,0,0,1,1,1,1]],[1,"8",1,[[0,-21,[9],10]],[5,985,18],[0,-290,0,0,0,0,1,1,1,1]],[1,"16+",1,[[0,-22,[11],12]],[5,73,93],[-427,-175,0,0,0,0,1,1,1,1]]],0,[0,0,1,0,0,1,0,-1,5,0,-2,6,0,-3,3,0,-4,2,0,-5,10,0,-6,11,0,-7,12,0,0,2,0,3,9,0,0,2,0,-1,8,0,0,3,0,-1,7,0,0,5,0,0,6,0,0,7,0,-1,9,0,0,10,0,0,11,0,0,12,0,4,4,1,5,4,22],[0,0,0,0,0,0,0,0,0,0,0,0,0,9],[-1,1,-1,-1,1,-1,1,-1,1,-1,1,-1,1,1],[0,1,0,0,2,0,3,0,4,0,5,0,6,7]],[[{"name":"progress_ed21642e-7181-491f-be10-9680838951c2","rect":[0,0,450,34],"offset":[0,0],"originalSize":[450,34],"capInsets":[0,0,0,0]}],[0],0,[0],[2],[8]],[[{"name":"loadBg","rect":[0,0,1386,640],"offset":[0,0],"originalSize":[1386,640],"capInsets":[0,0,0,0]}],[0],0,[0],[2],[9]],[[{"name":"clear","rect":[0,0,541,115],"offset":[0,0],"originalSize":[541,115],"capInsets":[0,0,0,0]}],[0],0,[0],[2],[10]],[[{"name":"8","rect":[0,0,985,18],"offset":[0,0],"originalSize":[985,18],"capInsets":[0,0,0,0]}],[0],0,[0],[2],[11]],[[{"name":"progressBg","rect":[0,0,462,46],"offset":[0,0],"originalSize":[462,46],"capInsets":[0,0,0,0]}],[0],0,[0],[2],[12]],[[{"name":"7","rect":[0,0,828,18],"offset":[0,0],"originalSize":[828,18],"capInsets":[0,0,0,0]}],[0],0,[0],[2],[13]],[[{"name":"16+","rect":[0,0,73,93],"offset":[0,0],"originalSize":[73,93],"capInsets":[0,0,0,0]}],[0],0,[0],[2],[14]]]]